MANIFEST.in
README.md
setup.py
jinja2modern/__init__.py
jinja2modern/parser_bin.py
jinja2modern/parser_error.py
jinja2modern/parser_inline.py
jinja2modern/utils.py
jinja2modern.egg-info/PKG-INFO
jinja2modern.egg-info/SOURCES.txt
jinja2modern.egg-info/dependency_links.txt
jinja2modern.egg-info/not-zip-safe
jinja2modern.egg-info/requires.txt
jinja2modern.egg-info/top_level.txt
jinja2modern/tags/__init__.py
jinja2modern/tags/coffee.py
jinja2modern/tags/js.py
jinja2modern/tags/less.py
jinja2modern/tags/sass.py
jinja2modern/tags/uglify.py
jinja2modern/templates/tags/css.html
jinja2modern/templates/tags/js.html