Metadata-Version: 1.0
Name: jinja2modern
Version: 0.3.0
Summary: Jinja2 tags for modern web. Includes sass, scss, less, coffee, uglify. Can be easily extended for any command line tools.
Home-page: https://github.com/velocityzen/jinja2modern
Author: Alexey Novikov
Author-email: velocityzen@gmail.com
License: BSD
Platform: UNKNOWN
